voluntrain/__init__.py
voluntrain/host.py
voluntrain/protocol.py
voluntrain/worker.py
voluntrain-0.1.1.dist-info/METADATA
voluntrain-0.1.1.dist-info/WHEEL
voluntrain-0.1.1.dist-info/entry_points.txt
voluntrain-0.1.1.dist-info/top_level.txt
voluntrain-0.1.1.dist-info/RECORD
