Metadata-Version: 2.4
Name: voluntrain
Version: 0.1.1
Summary: Decentralized Volunteer Computing Library for PyTorch
Author-email: Treamyracle <email.anda@example.com>
License: MIT
Project-URL: Homepage, https://github.com/Treamyracle/voluntrain
Project-URL: Bug Tracker, https://github.com/Treamyracle/voluntrain/issues
Classifier: Programming Language :: Python :: 3
Classifier: License :: OSI Approved :: MIT License
Classifier: Operating System :: OS Independent
Classifier: Topic :: Scientific/Engineering :: Artificial Intelligence
Requires-Python: >=3.8
Requires-Dist: torch>=2.0.0
Requires-Dist: pyzmq
Requires-Dist: cloudpickle
Requires-Dist: psutil
